README.md
setup.py
hi_spike/__init__.py
hi_spike/cmd_utils.py
hi_spike/gpu_queuer.py
hi_spike/io.py
hi_spike/redis_client.py
hi_spike/redis_maintainer.py
hi_spike/run_exp_plan.py
hi_spike/utils.py
hi_spike.egg-info/PKG-INFO
hi_spike.egg-info/SOURCES.txt
hi_spike.egg-info/dependency_links.txt
hi_spike.egg-info/entry_points.txt
hi_spike.egg-info/requires.txt
hi_spike.egg-info/top_level.txt